Metadata-Version: 2.1
Name: rainbowio
Version: 0.0.1
Summary: Simple pytohn library to make your cli programs more beautiful by adding colors to input and output functions
Home-page: UNKNOWN
Author: José Henrique
Author-email: josepicoli42@gmail.com
License: MIT License
Keywords: rainbowio
Platform: UNKNOWN
License-File: LICENSE
